metastruct/__init__.py
metastruct/basemeta.py
metastruct/basetypes/__init__.py
metastruct/basetypes/errtypes.py
metastruct/utils/__init__.py
metastruct/utils/json_tool.py
metastruct/validators/__init__.py
metastruct/validators/choice_validator.py
metastruct/validators/dict_validator.py
metastruct/validators/item_constructor.py
metastruct/validators/item_seq_validator.py
metastruct/validators/item_validator.py
metastruct/validators/list_validator.py
metastruct/validators/value_seq_validator.py
metavalidator-0.1.3.dist-info/METADATA
metavalidator-0.1.3.dist-info/WHEEL
metavalidator-0.1.3.dist-info/RECORD
